HVIS/__init__.py
HVIS/_core.py
HVIS-0.5.dist-info/License
HVIS-0.5.dist-info/METADATA
HVIS-0.5.dist-info/WHEEL
HVIS-0.5.dist-info/top_level.txt
HVIS-0.5.dist-info/RECORD
