Metadata-Version: 2.1
Name: HVIS
Version: 0.5
Summary: A library for extracting text from CAPTCHA images, easy to use for developers.
Author: Twinsszi
Author-email: adhm90879@gmail.com
Classifier: Programming Language :: Python :: 3
Classifier: License :: OSI Approved :: MIT License
Classifier: Operating System :: OS Independent
License-File: License
Requires-Dist: requests
Requires-Dist: user-agent
